krowten/models/__init__.py
krowten/models/base.py
krowten/models/graph.py
krowten/models/pandas_dataset.py
krowten/renderer/__init__.py
krowten/renderer/base.py
krowten/server.py
krowten-0.1.0.dist-info/LICENSE
krowten-0.1.0.dist-info/METADATA
krowten-0.1.0.dist-info/WHEEL
krowten-0.1.0.dist-info/RECORD
