Metadata-Version: 2.1
Name: krowten
Version: 0.1.0
Summary: A library for graphs and taking actions on them.
License: MIT
Author: utsavan
Requires-Python: >=3.10,<4.0
Classifier: License :: OSI Approved :: MIT License
Classifier: Programming Language :: Python :: 3
Classifier: Programming Language :: Python :: 3.10
Classifier: Programming Language :: Python :: 3.11
Requires-Dist: quart (>=0.18.4,<0.19.0)
